compress_utils/pyproject.toml
compress_utils/__init__.py
compress_utils/README.md
compress_utils/compress_utils_py.cpython-314-darwin.so
compress_utils/compress_utils_py.pyi
compress_utils-0.6.0.dist-info/RECORD
compress_utils-0.6.0.dist-info/WHEEL
compress_utils-0.6.0.dist-info/METADATA
compress_utils-0.6.0.dist-info/licenses/LICENSE
