Metadata-Version: 2.2
Name: compress-utils
Version: 0.6.0
Summary: Simple & high-performance compression utilities for Python
Keywords: compression,zlib,brotli,zstd,xz,lzma,utility,performance
Author-Email: Nicolas Dupont <nicolas@dupontcyborg.com>
License: MIT
Classifier: Intended Audience :: Developers
Classifier: License :: OSI Approved :: MIT License
Classifier: Programming Language :: Python :: 3
Classifier: Programming Language :: Python :: 3.10
Classifier: Programming Language :: Python :: 3.11
Classifier: Programming Language :: Python :: 3.12
Classifier: Programming Language :: Python :: 3.13
Classifier: Programming Language :: Python :: 3.14
Classifier: Programming Language :: C++
Classifier: Operating System :: OS Independent
Classifier: Topic :: System :: Archiving :: Compression
Classifier: Topic :: Software Development :: Libraries
Project-URL: Homepage, https://github.com/dupontcyborg/compress-utils
Project-URL: Documentation, https://github.com/dupontcyborg/compress-utils#readme
Project-URL: Repository, https://github.com/dupontcyborg/compress-utils
Project-URL: Bug Tracker, https://github.com/dupontcyborg/compress-utils/issues
Requires-Python: >=3.10
